gym_http_server/__init__.py
gym_http_server/command_line.py
gym_http_server/example_agent.py
gym_http_server/example_client.py
gym_http_server/gym_http_client.py
gym_http_server-0.0.1.dist-info/LICENSE
gym_http_server-0.0.1.dist-info/METADATA
gym_http_server-0.0.1.dist-info/WHEEL
gym_http_server-0.0.1.dist-info/entry_points.txt
gym_http_server-0.0.1.dist-info/top_level.txt
gym_http_server-0.0.1.dist-info/RECORD
