Metadata-Version: 2.1
Name: gym-http-server
Version: 0.0.1
Summary: Serve gym on a webserver and receive HTTP requests to play to the game from any client
Home-page: https://github.com/saravanabalagi/gym-http-server
Author: Saravanabalagi Ramachandran
Author-email: saravanabalagi@hotmail.com
License: MIT
Platform: UNKNOWN
Classifier: Development Status :: 3 - Alpha
Classifier: Topic :: Software Development :: Libraries
Classifier: License :: OSI Approved :: MIT License
Classifier: Programming Language :: Python :: 3
Classifier: Programming Language :: Python :: 3.6
Classifier: Programming Language :: Python :: 3.7
Requires-Dist: Flask (==0.12.3)
Requires-Dist: numpy
Requires-Dist: gym (==0.7.4)
Requires-Dist: requests (==2.21.0)
Requires-Dist: pytest
